face_detection_lib/__init__.py
face_detection_lib/detector.py
face_detection_lib/models/best.pt
face_detection_lib-0.8.dist-info/LICENSE
face_detection_lib-0.8.dist-info/METADATA
face_detection_lib-0.8.dist-info/WHEEL
face_detection_lib-0.8.dist-info/top_level.txt
face_detection_lib-0.8.dist-info/RECORD
